figment/__init__.py
figment/__main__.py
figment/config.py
figment/decorators.py
figment/exception.py
figment/launcher.py
figment/runner.py
figment/sentinel.py
figment/structs.py
figment/template.py
figment_config-0.1.1.dist-info/METADATA
figment_config-0.1.1.dist-info/WHEEL
figment_config-0.1.1.dist-info/entry_points.txt
figment_config-0.1.1.dist-info/top_level.txt
figment_config-0.1.1.dist-info/RECORD
