Metadata-Version: 2.1
Name: figment-config
Version: 0.1.1
Summary: Configuration management tool
Home-page: https://www.nuradius.com
Author: Nuradius Software
Author-email: todd@datacomponents.net
License: Apache Software License
Platform: UNKNOWN
Classifier: Development Status :: 5 - Production/Stable
Classifier: Intended Audience :: Developers
Classifier: License :: OSI Approved :: Apache Software License
Classifier: Programming Language :: Python
Classifier: Programming Language :: Python :: 3
Classifier: Programming Language :: Python :: 3.5
Classifier: Programming Language :: Python :: 3.6
Classifier: Programming Language :: Python :: 3.7
Classifier: Programming Language :: Python :: 3.8
Requires-Python: >=3.5
Requires-Dist: Flask (==1.1.2)
Requires-Dist: Jinja2 (==2.11.3)
Requires-Dist: MarkupSafe (==1.1.1)
Requires-Dist: PyYAML (==5.3.1)
Requires-Dist: Werkzeug (==1.0.1)
Requires-Dist: click (==7.1.2)
Requires-Dist: itsdangerous (==1.1.0)
